FinanceAnalysis-0.0.1.1.dist-info/METADATA
FinanceAnalysis-0.0.1.1.dist-info/RECORD
FinanceAnalysis-0.0.1.1.dist-info/WHEEL
FinanceAnalysis-0.0.1.1.dist-info/top_level.txt
KLineAnalysis/GetDate.py
KLineAnalysis/KLineFeatures.py
KLineAnalysis/TrendAnalysis.py
KLineAnalysis/__init__.py
