Metadata-Version: 2.1
Name: FinanceAnalysis
Version: 0.0.1.1
Summary: this is a Finance Analysis System
Home-page: https://github.com/670428704/FinanceAnalysis.git
Author: fdsn
Author-email: 670428704@qq.com
License: UNKNOWN
Platform: UNKNOWN
Requires-Dist: tushare
Requires-Dist: numpy
